ht_serve/__init__.py
ht_serve/cli.py
ht_serve/server.py
ht_serve/templates/inject.js
ht_serve/testsite/index.html
ht_serve/testsite/script.js
ht_serve/testsite/styles.css
ht_serve-0.0.3.dist-info/METADATA
ht_serve-0.0.3.dist-info/WHEEL
ht_serve-0.0.3.dist-info/entry_points.txt
ht_serve-0.0.3.dist-info/top_level.txt
ht_serve-0.0.3.dist-info/RECORD
