Metadata-Version: 2.4
Name: ht-serve
Version: 0.0.3
Summary: A secure HTTPS live reload server for front-end prototyping and dashboard development
Home-page: https://github.com/HermiTech-LLC/HT-Serve
Author: HermiTech Labs
Author-email: support@hermitech.dev
License: MIT
Project-URL: Homepage, https://github.com/HermiTech-LLC/HT-Serve
Project-URL: Documentation, https://github.com/HermiTech-LLC/HT-Serve#readme
Project-URL: Issues, https://github.com/HermiTech-LLC/HT-Serve/issues
Project-URL: Source, https://github.com/HermiTech-LLC/HT-Serve
Keywords: https,tls,live-reload,webdev,dashboard,frontend,hot-reload,dev-server
Classifier: Development Status :: 5 - Production/Stable
Classifier: Environment :: Console
Classifier: Framework :: AsyncIO
Classifier: Intended Audience :: Developers
Classifier: License :: OSI Approved :: MIT License
Classifier: Programming Language :: Python :: 3
Classifier: Programming Language :: Python :: 3.8
Classifier: Topic :: Internet :: WWW/HTTP :: HTTP Servers
Classifier: Topic :: Software Development :: Testing
Classifier: Topic :: Software Development :: User Interfaces
Classifier: Typing :: Typed
Requires-Python: >=3.8
Requires-Dist: watchdog>=3.0
Requires-Dist: rich>=13.0
Requires-Dist: websockets>=11.0
Requires-Dist: typer[all]>=0.9
Dynamic: author-email
Dynamic: home-page
Dynamic: requires-python
